SplitMerge/__init__.py
SplitMerge/clsLog.py
SplitMerge/clsMergeFiles.py
SplitMerge/clsSplitFiles.py
SplitMerge-0.0.2.post3.dist-info/LICENSE
SplitMerge-0.0.2.post3.dist-info/METADATA
SplitMerge-0.0.2.post3.dist-info/WHEEL
SplitMerge-0.0.2.post3.dist-info/top_level.txt
SplitMerge-0.0.2.post3.dist-info/RECORD
