Metadata-Version: 2.1
Name: SplitMerge
Version: 0.0.2.post3
Summary: Split & Merge utilities for large csv files.
Home-page: https://github.com/SatyakiDe2019/SplitMerge
Author: Satyaki De
Author-email: satyaki.de@gmail.com
License: UNKNOWN
Platform: UNKNOWN
Classifier: Programming Language :: Python :: 3
Classifier: License :: OSI Approved :: MIT License
Classifier: Operating System :: OS Independent
Requires-Dist: markdown
Requires-Dist: pandas
Requires-Dist: regex
